deampgen_password_generator/__init__.py
deampgen_password_generator/main.py
deampgen_password_generator-1.0.0.dist-info/METADATA
deampgen_password_generator-1.0.0.dist-info/WHEEL
deampgen_password_generator-1.0.0.dist-info/top_level.txt
deampgen_password_generator-1.0.0.dist-info/RECORD
