Metadata-Version: 2.2
Name: deampgen_password_generator
Version: 1.0.0
Summary: A simple password generator library
Author: Sergey
Classifier: Programming Language :: Python :: 3
Classifier: License :: OSI Approved :: MIT License
Classifier: Operating System :: OS Independent
Requires-Python: >=3.6
Dynamic: author
Dynamic: classifier
Dynamic: requires-python
Dynamic: summary
